hydrology_api.py
hydrology_api_uk_client-0.0.1.dist-info/LICENCE
hydrology_api_uk_client-0.0.1.dist-info/METADATA
hydrology_api_uk_client-0.0.1.dist-info/WHEEL
hydrology_api_uk_client-0.0.1.dist-info/top_level.txt
hydrology_api_uk_client-0.0.1.dist-info/RECORD
