Metadata-Version: 2.1
Name: hydrology_api_uk_client
Version: 0.0.1
Summary: Load data from the UK Hydology API
Author-email: Edward Jex <edwardjex@live.co.uk>
Keywords: Hydology,API,UK,Water,Data,Environment Agency,River
Classifier: License :: OSI Approved :: MIT License
Classifier: Programming Language :: Python
Classifier: Programming Language :: Python :: 3
Requires-Python: >=3.9
License-File: LICENCE
Requires-Dist: pandas
Requires-Dist: numpy
Requires-Dist: urllib3
Requires-Dist: ujson
